TestResultDBAccess/DBAccessFactory.py
TestResultDBAccess/TestResultDBAccess.pdf
TestResultDBAccess/__init__.py
TestResultDBAccess/version.py
TestResultDBAccess/DBAccess/__init__.py
TestResultDBAccess/DBAccess/db_access_interface.py
TestResultDBAccess/DBAccess/direct_db_access.py
TestResultDBAccess/DBAccess/rest_api_db_access.py
TestResultDBAccess-0.1.6.dist-info/METADATA
TestResultDBAccess-0.1.6.dist-info/WHEEL
TestResultDBAccess-0.1.6.dist-info/top_level.txt
TestResultDBAccess-0.1.6.dist-info/RECORD
