Metadata-Version: 2.1
Name: TestResultDBAccess
Version: 0.1.6
Summary: Interfaces to access TestResultWebApp database
Home-page: https://github.com/test-fullautomation/python-testresultdbaccess
Author: Tran Duy Ngoan
Author-email: Ngoan.TranDuy@vn.bosch.com
License: UNKNOWN
Platform: UNKNOWN
Classifier: Programming Language :: Python :: 3
Classifier: License :: OSI Approved :: Apache Software License
Classifier: Operating System :: OS Independent
Classifier: Development Status :: 4 - Beta
Classifier: Intended Audience :: Developers
Classifier: Topic :: Software Development
Requires-Python: >=3.0
Requires-Dist: mysqlclient
Requires-Dist: requests-kerberos
